{"activity_name": "Users", "request_id": 3, "is_keyboard_deployed": false, "activity": {"added_fragments": ["1"], "active_fragments": ["1"], "root": {"class": "hierarchy", "visibility": "visible", "children": [{"class": "android.widget.FrameLayout", "visibility": "", "children": [{"class": "android.widget.LinearLayout", "visibility": "", "children": [{"class": "android.widget.FrameLayout", "visibility": "", "children": [{"class": "android.widget.LinearLayout", "visibility": "", "children": [{"class": "android.widget.FrameLayout", "visibility": "", "children": [{"class": "android.support.v4.widget.DrawerLayout", "visibility": "", "children": [{"class": "android.widget.FrameLayout", "visibility": "", "children": [{"class": "android.widget.FrameLayout", "visibility": "", "children": [{"class": "android.view.ViewGroup", "visibility": "visible", "children": [{"class": "android.widget.ImageButton", "visibility": "visible", "bounds": [0, 63, 147, 210]}, {"class": "android.support.v7.widget.LinearLayoutCompat", "visibility": "", "children": [{"class": "android.widget.LinearLayout", "visibility": "", "children": [{"class": "android.widget.LinearLayout", "visibility": "", "children": [{"class": "android.widget.ImageView", "visibility": "visible", "bounds": [168, 117, 252, 156]}, {"class": "android.widget.LinearLayout", "visibility": "", "children": [{"class": "android.widget.EditText", "visibility": "visible", "text": "I'm shopping for ...", "bounds": [252, 87, 1017, 182]}], "bounds": [252, 63, 1017, 210]}], "bounds": [147, 63, 1017, 210]}], "bounds": [147, 63, 1038, 210]}], "bounds": [147, 63, 1038, 210]}], "bounds": [0, 63, 1080, 210]}], "bounds": [0, 63, 1080, 210]}, {"class": "android.widget.FrameLayout", "visibility": "", "children": [{"class": "android.widget.LinearLayout", "visibility": "", "children": [{"class": "android.widget.FrameLayout", "visibility": "", "children": [{"class": "android.widget.FrameLayout", "visibility": "", "children": [{"class": "android.widget.FrameLayout", "visibility": "", "children": [{"class": "android.widget.ScrollView", "visibility": "visible", "children": [{"class": "android.widget.LinearLayout", "visibility": "", "children": [{"class": "android.widget.LinearLayout", "visibility": "", "children": [{"class": "android.widget.LinearLayout", "visibility": "", "children": [{"class": "android.widget.TextView", "visibility": "visible", "text": "Recent Searches", "bounds": [42, 255, 1038, 320]}], "bounds": [42, 255, 1038, 352]}, {"class": "android.widget.LinearLayout", "visibility": "", "children": [{"class": "android.widget.TextView", "visibility": "visible", "text": "wallets for women", "bounds": [42, 352, 1038, 457]}, {"class": "android.widget.TextView", "visibility": "visible", "text": "book", "bounds": [42, 457, 1038, 562]}, {"class": "android.widget.TextView", "visibility": "visible", "text": "aa", "bounds": [42, 562, 1038, 667]}], "bounds": [42, 352, 1038, 667]}], "bounds": [0, 213, 1080, 709]}, {"class": "android.widget.LinearLayout", "visibility": "", "children": [{"class": "android.widget.LinearLayout", "visibility": "", "children": [{"class": "android.widget.TextView", "visibility": "visible", "text": "Recently Viewed", "bounds": [42, 754, 856, 819]}, {"class": "android.widget.TextView", "visibility": "visible", "text": "View All", "bounds": [856, 758, 1080, 814]}], "bounds": [42, 754, 1080, 851]}, {"class": "android.widget.HorizontalScrollView", "visibility": "visible", "children": [{"class": "android.widget.FrameLayout", "visibility": "", "children": [{"class": "android.widget.ImageView", "visibility": "visible", "bounds": [42, 851, 278, 1019]}, {"class": "android.widget.ImageView", "visibility": "visible", "bounds": [299, 851, 535, 1019]}], "bounds": [42, 851, 535, 1019]}], "bounds": [42, 851, 1080, 1019]}], "bounds": [0, 712, 1080, 1019]}], "bounds": [0, 210, 1080, 1019]}], "bounds": [0, 210, 1080, 1019]}], "bounds": [0, 210, 1080, 1019]}], "bounds": [0, 210, 1080, 1019]}], "bounds": [0, 210, 1080, 1019]}], "bounds": [0, 210, 1080, 1019]}], "bounds": [0, 210, 1080, 1019]}], "bounds": [0, 63, 1080, 1019]}], "bounds": [0, 63, 1080, 1019]}], "bounds": [0, 63, 1080, 1019]}], "bounds": [0, 63, 1080, 1019]}], "bounds": [0, 63, 1080, 1019]}], "bounds": [0, 0, 1080, 1794]}], "bounds": [0, 0, 1080, 1794]}], "bounds": [0, 0, 1440, 2560]}}}