{"activity_name": "Users", "request_id": 3, "is_keyboard_deployed": false, "activity": {"added_fragments": ["1"], "active_fragments": ["1"], "root": {"class": "hierarchy", "visibility": "visible", "children": [{"class": "android.widget.FrameLayout", "visibility": "", "children": [{"class": "android.widget.LinearLayout", "visibility": "", "children": [{"class": "android.widget.FrameLayout", "visibility": "", "children": [{"class": "android.widget.LinearLayout", "visibility": "", "children": [{"class": "android.widget.LinearLayout", "visibility": "", "children": [{"class": "android.widget.FrameLayout", "visibility": "", "children": [{"class": "android.widget.LinearLayout", "visibility": "", "children": [{"class": "android.widget.FrameLayout", "visibility": "", "children": [{"class": "android.widget.ImageView", "visibility": "visible", "bounds": [894, 433, 957, 486]}], "bounds": [81, 391, 999, 486]}, {"class": "android.widget.LinearLayout", "visibility": "", "children": [{"class": "android.widget.TextView", "visibility": "visible", "text": "Choose a Wishlist", "bounds": [223, 486, 857, 593]}, {"class": "android.view.View", "visibility": "visible", "bounds": [144, 593, 936, 596]}, {"class": "android.view.View", "visibility": "visible", "bounds": [144, 1252, 936, 1255]}, {"class": "android.widget.ListView", "visibility": "visible", "children": [{"class": "android.widget.LinearLayout", "visibility": "", "children": [{"class": "android.widget.ImageView", "visibility": "visible", "bounds": [270, 627, 365, 722]}, {"class": "android.widget.TextView", "visibility": "visible", "text": "Wishlist #1", "bounds": [407, 596, 936, 754]}], "bounds": [144, 596, 936, 754]}], "bounds": [144, 596, 936, 1252]}, {"class": "android.widget.LinearLayout", "visibility": "", "children": [{"class": "android.widget.LinearLayout", "visibility": "", "children": [{"class": "android.widget.ImageView", "visibility": "visible", "bounds": [635, 1307, 678, 1349]}, {"class": "android.widget.TextView", "visibility": "visible", "text": "New Wishlist", "bounds": [691, 1297, 936, 1360]}], "bounds": [635, 1297, 936, 1360]}], "bounds": [144, 1255, 936, 1360]}], "bounds": [81, 486, 999, 1402]}], "bounds": [81, 391, 999, 1402]}], "bounds": [81, 391, 999, 1402]}], "bounds": [0, 0, 1080, 1794]}], "bounds": [0, 0, 1080, 1794]}], "bounds": [0, 0, 1080, 1794]}], "bounds": [0, 0, 1080, 1794]}], "bounds": [0, 0, 1080, 1794]}], "bounds": [0, 0, 1440, 2560]}}}