{"activity_name": "Users", "request_id": 3, "is_keyboard_deployed": false, "activity": {"added_fragments": ["1"], "active_fragments": ["1"], "root": {"class": "hierarchy", "visibility": "visible", "children": [{"class": "android.widget.FrameLayout", "visibility": "", "children": [{"class": "android.widget.FrameLayout", "visibility": "", "children": [{"class": "android.widget.FrameLayout", "visibility": "", "children": [{"class": "android.widget.FrameLayout", "visibility": "", "children": [{"class": "android.widget.FrameLayout", "visibility": "", "children": [{"class": "android.widget.FrameLayout", "visibility": "", "children": [{"class": "android.widget.FrameLayout", "visibility": "", "children": [{"class": "android.widget.FrameLayout", "visibility": "", "children": [{"class": "android.widget.FrameLayout", "visibility": "", "children": [{"class": "android.support.v7.widget.RecyclerView", "visibility": "visible", "children": [{"class": "android.widget.FrameLayout", "visibility": "", "children": [{"class": "android.widget.LinearLayout", "visibility": "", "children": [{"class": "android.widget.FrameLayout", "visibility": "", "children": [{"class": "android.support.v4.view.ViewPager", "visibility": "visible", "children": [{"class": "android.widget.RelativeLayout", "visibility": "", "children": [{"class": "android.widget.ImageView", "visibility": "visible", "bounds": [0, 0, 1080, 1080]}, {"class": "android.widget.ImageView", "visibility": "visible", "bounds": [477, 477, 603, 603]}], "bounds": [0, 0, 1080, 1080]}], "bounds": [0, 0, 1080, 1080]}, {"class": "android.view.View", "visibility": "visible", "bounds": [42, 1006, 273, 1038]}], "bounds": [0, 0, 1080, 1080]}], "bounds": [0, 0, 1080, 1080]}], "bounds": [0, 0, 1080, 1080]}, {"class": "android.widget.FrameLayout", "visibility": "", "children": [{"class": "android.widget.LinearLayout", "visibility": "", "children": [{"class": "android.widget.FrameLayout", "visibility": "", "children": [{"class": "android.widget.ImageView", "visibility": "visible", "bounds": [0, 1080, 1080, 1206]}, {"class": "android.view.ViewGroup", "visibility": "visible", "children": [{"class": "android.widget.LinearLayout", "visibility": "", "children": [{"class": "android.widget.LinearLayout", "visibility": "", "children": [{"class": "android.widget.ImageView", "visibility": "visible", "bounds": [42, 1088, 45, 1141]}, {"class": "android.widget.TextView", "visibility": "visible", "text": "Trend Spotting", "bounds": [56, 1093, 267, 1136]}], "bounds": [42, 1088, 267, 1141]}, {"class": "android.widget.TextView", "visibility": "visible", "text": "US $4.00 - 4.53", "bounds": [42, 1141, 334, 1198]}], "bounds": [42, 1088, 334, 1198]}, {"class": "android.widget.FrameLayout", "visibility": "", "children": [{"class": "android.widget.ImageView", "visibility": "visible", "bounds": [846, 1080, 1080, 1206]}, {"class": "android.widget.LinearLayout", "visibility": "", "children": [{"class": "android.widget.TextView", "visibility": "visible", "text": "Starts in", "bounds": [909, 1098, 1016, 1137]}, {"class": "android.view.View", "visibility": "visible", "bounds": [909, 1145, 1038, 1187]}], "bounds": [846, 1080, 1080, 1206]}], "bounds": [846, 1080, 1080, 1206]}], "bounds": [0, 1080, 1080, 1206]}], "bounds": [0, 1080, 1080, 1206]}], "bounds": [0, 1080, 1080, 1206]}], "bounds": [0, 1080, 1080, 1206]}, {"class": "android.widget.FrameLayout", "visibility": "", "children": [{"class": "android.widget.LinearLayout", "visibility": "", "bounds": [0, 1206, 1080, 1248]}], "bounds": [0, 1206, 1080, 1248]}, {"class": "android.widget.FrameLayout", "visibility": "", "children": [{"class": "android.widget.LinearLayout", "visibility": "", "children": [{"class": "android.widget.RelativeLayout", "visibility": "", "children": [{"class": "android.view.ViewGroup", "visibility": "visible", "children": [{"class": "android.widget.TextView", "visibility": "visible", "text": "US $4.17 - 4.72", "bounds": [42, 1259, 410, 1330]}], "bounds": [42, 1259, 954, 1330]}, {"class": "android.view.ViewGroup", "visibility": "visible", "children": [{"class": "android.widget.TextView", "visibility": "visible", "text": "US $8.17 - 9.25", "bounds": [42, 1341, 257, 1397]}, {"class": "android.view.ViewGroup", "visibility": "visible", "children": [{"class": "android.widget.TextView", "visibility": "visible", "text": "-49%", "bounds": [273, 1346, 354, 1392]}], "bounds": [273, 1341, 365, 1397]}], "bounds": [42, 1341, 948, 1397]}, {"class": "android.widget.FrameLayout", "visibility": "", "children": [{"class": "android.view.View", "visibility": "visible", "bounds": [970, 1248, 1054, 1332]}, {"class": "android.view.View", "visibility": "visible", "bounds": [970, 1248, 1054, 1332]}, {"class": "android.widget.ImageView", "visibility": "visible", "bounds": [983, 1261, 1041, 1319]}], "bounds": [970, 1248, 1054, 1332]}, {"class": "android.widget.TextView", "visibility": "visible", "text": "1942", "bounds": [964, 1332, 1059, 1375]}], "bounds": [0, 1248, 1080, 1408]}], "bounds": [0, 1248, 1080, 1408]}], "bounds": [0, 1248, 1080, 1408]}, {"class": "android.widget.FrameLayout", "visibility": "", "children": [{"class": "android.widget.LinearLayout", "visibility": "", "children": [{"class": "android.widget.TextView", "visibility": "visible", "text": "Fashion Leather Wallet Men Luxury Slim Coin Purse Business Foldable Wallet Man Card Holder Pocket Clutch Male Handbags Tote Bag", "bounds": [0, 1408, 1080, 1651]}], "bounds": [0, 1408, 1080, 1651]}], "bounds": [0, 1408, 1080, 1651]}, {"class": "android.widget.FrameLayout", "visibility": "", "children": [{"class": "android.widget.LinearLayout", "visibility": "", "children": [{"class": "android.widget.LinearLayout", "visibility": "", "children": [{"class": "android.widget.TextView", "visibility": "visible", "text": "4.8", "bounds": [42, 1651, 86, 1694]}, {"class": "android.widget.TextView", "visibility": "visible", "text": "2462 orders", "bounds": [263, 1651, 435, 1694]}, {"class": "android.widget.RatingBar", "visibility": "visible", "text": "48.0", "bounds": [97, 1659, 242, 1685]}], "bounds": [42, 1651, 435, 1694]}], "bounds": [0, 1651, 1080, 1726]}], "bounds": [0, 1651, 1080, 1726]}, {"class": "android.widget.FrameLayout", "visibility": "", "children": [{"class": "android.widget.LinearLayout", "visibility": "", "children": [{"class": "android.widget.LinearLayout", "visibility": "", "children": [{"class": "android.view.View", "visibility": "visible", "bounds": [42, 1726, 1038, 1727]}, {"class": "android.widget.LinearLayout", "visibility": "", "children": [{"class": "android.widget.TextView", "visibility": "visible", "text": "Free Shipping", "bounds": [32, 1748, 307, 1794]}], "bounds": [32, 1727, 1048, 1794]}], "bounds": [0, 1726, 1080, 1794]}], "bounds": [0, 1726, 1080, 1794]}], "bounds": [0, 1726, 1080, 1794]}], "bounds": [0, 0, 1080, 1794]}, {"class": "android.widget.FrameLayout", "visibility": "", "children": [{"class": "android.widget.LinearLayout", "visibility": "", "children": [{"class": "android.widget.FrameLayout", "visibility": "", "children": [{"class": "android.widget.RelativeLayout", "visibility": "", "children": [{"class": "android.widget.LinearLayout", "visibility": "", "children": [{"class": "android.view.View", "visibility": "visible", "bounds": [0, 1647, 1080, 1660]}, {"class": "android.widget.LinearLayout", "visibility": "", "children": [{"class": "android.widget.LinearLayout", "visibility": "", "children": [{"class": "android.widget.ImageView", "visibility": "visible", "bounds": [47, 1677, 110, 1740]}, {"class": "android.widget.TextView", "visibility": "visible", "text": "STORE", "bounds": [41, 1743, 117, 1776]}], "bounds": [0, 1660, 158, 1794]}, {"class": "android.widget.LinearLayout", "visibility": "", "children": [{"class": "android.widget.TextView", "visibility": "visible", "text": "ADD TO CART", "bounds": [271, 1701, 506, 1752]}], "bounds": [158, 1660, 619, 1794]}, {"class": "android.widget.Button", "visibility": "visible", "text": "BUY NOW", "bounds": [619, 1660, 1080, 1794]}], "bounds": [0, 1660, 1080, 1794]}], "bounds": [0, 1647, 1080, 1794]}], "bounds": [0, 1647, 1080, 1794]}], "bounds": [0, 1647, 1080, 1794]}], "bounds": [0, 1647, 1080, 1794]}], "bounds": [0, 1647, 1080, 1794]}], "bounds": [0, 0, 1080, 1794]}], "bounds": [0, 0, 1080, 1794]}], "bounds": [0, 0, 1080, 1794]}, {"class": "android.widget.LinearLayout", "visibility": "", "children": [{"class": "android.view.ViewGroup", "visibility": "visible", "children": [{"class": "android.widget.ImageButton", "visibility": "visible", "bounds": [0, 63, 147, 210]}, {"class": "android.widget.TextView", "visibility": "visible", "text": "Detail", "bounds": [189, 105, 310, 168]}, {"class": "android.support.v7.widget.LinearLayoutCompat", "visibility": "", "children": [{"class": "android.widget.FrameLayout", "visibility": "", "children": [{"class": "android.widget.ImageView", "visibility": "visible", "bounds": [733, 73, 795, 199]}], "bounds": [701, 73, 827, 199]}, {"class": "android.widget.FrameLayout", "visibility": "", "children": [{"class": "android.widget.ImageView", "visibility": "visible", "bounds": [986, 73, 1048, 199]}], "bounds": [954, 73, 1080, 199]}, {"class": "android.widget.TextView", "visibility": "visible", "bounds": [827, 73, 954, 199]}], "bounds": [701, 63, 1080, 210]}], "bounds": [0, 0, 1080, 210]}], "bounds": [0, 0, 1080, 231]}], "bounds": [0, 0, 1080, 1794]}], "bounds": [0, 0, 1080, 1794]}], "bounds": [0, 0, 1080, 1794]}], "bounds": [0, 0, 1080, 1794]}], "bounds": [0, 0, 1080, 1794]}], "bounds": [0, 0, 1080, 1794]}], "bounds": [0, 0, 1440, 2560]}}}