[{"screenId": 83, "screenTap": [{"confidence": 1.0, "confidenceOpacity": null, "frame": null, "x": 778.5088491439819, "y": 1164.0535354614258}]}, {"screenId": 84, "screenTap": [{"confidence": 1.0, "confidenceOpacity": null, "frame": null, "x": 740.8476090431213, "y": 1166.0616302490234}]}, {"screenId": 85, "screenTap": [{"confidence": 1.0, "confidenceOpacity": null, "frame": null, "x": 740.836569070816, "y": 1166.0730743408203}]}, {"screenId": 86, "screenTap": [{"confidence": 1.0, "confidenceOpacity": null, "frame": null, "x": 652.9464483261108, "y": 1173.9692687988281}]}, {"screenId": 87, "screenTap": [{"confidence": 1.0, "confidenceOpacity": null, "frame": null, "x": 521.6258811950684, "y": 1186.0536575317383}]}, {"screenId": 88, "screenTap": [{"confidence": 1.0, "confidenceOpacity": null, "frame": null, "x": 464.8090499639511, "y": 1186.4144897460938}]}, {"screenId": 89, "screenTap": [{"confidence": 1.0, "confidenceOpacity": null, "frame": null, "x": 464.6663510799408, "y": 1186.3426208496094}]}, {"screenId": 90, "screenTap": [{"confidence": 1.0, "confidenceOpacity": null, "frame": null, "x": 464.5872688293457, "y": 1186.5918731689453}]}, {"screenId": 91, "screenTap": [{"confidence": 1.0, "confidenceOpacity": null, "frame": null, "x": 464.72644329071045, "y": 1186.3706588745117}]}, {"screenId": 92, "screenTap": [{"confidence": 1.0, "confidenceOpacity": null, "frame": null, "x": 464.5901817083359, "y": 1186.2397384643555}]}, {"screenId": 93, "screenTap": [{"confidence": 0.7856566309928894, "confidenceOpacity": null, "frame": null, "x": 464.8624312877655, "y": 1186.6144180297852}]}, {"screenId": 117, "screenTap": [{"confidence": 1.0, "confidenceOpacity": null, "frame": null, "x": 245.07540374994278, "y": 1186.838264465332}]}, {"screenId": 118, "screenTap": [{"confidence": 1.0, "confidenceOpacity": null, "frame": null, "x": 262.0737424492836, "y": 1186.764793395996}]}, {"screenId": 119, "screenTap": [{"confidence": 1.0, "confidenceOpacity": null, "frame": null, "x": 262.08257764577866, "y": 1186.8513107299805}]}, {"screenId": 120, "screenTap": [{"confidence": 1.0, "confidenceOpacity": null, "frame": null, "x": 313.8158315420151, "y": 1187.1894836425781}]}, {"screenId": 121, "screenTap": [{"confidence": 1.0, "confidenceOpacity": null, "frame": null, "x": 487.1352857351303, "y": 1185.9515762329102}]}, {"screenId": 122, "screenTap": [{"confidence": 1.0, "confidenceOpacity": null, "frame": null, "x": 600.8003783226013, "y": 1185.999755859375}]}, {"screenId": 123, "screenTap": [{"confidence": 1.0, "confidenceOpacity": null, "frame": null, "x": 645.256222486496, "y": 1186.2773895263672}]}, {"screenId": 124, "screenTap": [{"confidence": 1.0, "confidenceOpacity": null, "frame": null, "x": 645.1389992237091, "y": 1186.2459182739258}]}, {"screenId": 125, "screenTap": [{"confidence": 1.0, "confidenceOpacity": null, "frame": null, "x": 645.0607216358185, "y": 1186.1582565307617}]}, {"screenId": 126, "screenTap": [{"confidence": 1.0, "confidenceOpacity": null, "frame": null, "x": 644.9827337265015, "y": 1186.2694931030273}]}, {"screenId": 127, "screenTap": [{"confidence": 1.0, "confidenceOpacity": null, "frame": null, "x": 645.2480149269104, "y": 1185.9617614746094}]}, {"screenId": 128, "screenTap": [{"confidence": 0.9874820709228516, "confidenceOpacity": null, "frame": null, "x": 645.6024205684662, "y": 1186.3209915161133}]}, {"screenId": 151, "screenTap": [{"confidence": 0.7790989279747009, "confidenceOpacity": null, "frame": null, "x": 526.6225630044937, "y": 1662.2656631469727}]}, {"screenId": 152, "screenTap": [{"confidence": 0.9593105912208557, "confidenceOpacity": null, "frame": null, "x": 526.4005243778229, "y": 1662.3863983154297}]}, {"screenId": 153, "screenTap": [{"confidence": 0.9480104446411133, "confidenceOpacity": null, "frame": null, "x": 526.4302164316177, "y": 1662.275047302246}]}, {"screenId": 155, "screenTap": [{"confidence": 1.0, "confidenceOpacity": null, "frame": null, "x": 525.179255604744, "y": 1663.5364151000977}]}, {"screenId": 156, "screenTap": [{"confidence": 1.0, "confidenceOpacity": null, "frame": null, "x": 525.2240753173828, "y": 1664.7869110107422}]}, {"screenId": 157, "screenTap": [{"confidence": 1.0, "confidenceOpacity": null, "frame": null, "x": 525.1877045631409, "y": 1664.7267150878906}]}, {"screenId": 158, "screenTap": [{"confidence": 1.0, "confidenceOpacity": null, "frame": null, "x": 525.1673144102097, "y": 1664.9610900878906}]}, {"screenId": 159, "screenTap": [{"confidence": 1.0, "confidenceOpacity": null, "frame": null, "x": 525.1285296678543, "y": 1664.564094543457}]}, {"screenId": 193, "screenTap": [{"confidence": 1.0, "confidenceOpacity": null, "frame": null, "x": 147.289557158947, "y": 1438.4334182739258}]}, {"screenId": 194, "screenTap": [{"confidence": 1.0, "confidenceOpacity": null, "frame": null, "x": 147.13729485869408, "y": 1438.2518005371094}]}, {"screenId": 195, "screenTap": [{"confidence": 1.0, "confidenceOpacity": null, "frame": null, "x": 147.2095012664795, "y": 1438.2013320922852}]}, {"screenId": 196, "screenTap": [{"confidence": 1.0, "confidenceOpacity": null, "frame": null, "x": 146.99498623609543, "y": 1437.8590393066406}]}, {"screenId": 197, "screenTap": [{"confidence": 1.0, "confidenceOpacity": null, "frame": null, "x": 147.03828513622284, "y": 1438.1222534179688}]}, {"screenId": 198, "screenTap": [{"confidence": 1.0, "confidenceOpacity": null, "frame": null, "x": 147.14213892817497, "y": 1439.267692565918}]}, {"screenId": 199, "screenTap": [{"confidence": 1.0, "confidenceOpacity": null, "frame": null, "x": 147.07779809832573, "y": 1439.8562622070312}]}, {"screenId": 200, "screenTap": [{"confidence": 1.0, "confidenceOpacity": null, "frame": null, "x": 147.45196223258972, "y": 1442.0936965942383}]}, {"screenId": 201, "screenTap": [{"confidence": 1.0, "confidenceOpacity": null, "frame": null, "x": 147.29240164160728, "y": 1437.2339630126953}]}, {"screenId": 202, "screenTap": [{"confidence": 1.0, "confidenceOpacity": null, "frame": null, "x": 147.21024557948112, "y": 1437.2346496582031}]}, {"screenId": 385, "screenTap": [{"confidence": 1.0, "confidenceOpacity": null, "frame": null, "x": 728.3021128177643, "y": 1240.7099533081055}]}, {"screenId": 386, "screenTap": [{"confidence": 1.0, "confidenceOpacity": null, "frame": null, "x": 728.3910441398621, "y": 1240.7131576538086}]}, {"screenId": 387, "screenTap": [{"confidence": 1.0, "confidenceOpacity": null, "frame": null, "x": 728.2087397575378, "y": 1240.5457305908203}]}, {"screenId": 388, "screenTap": [{"confidence": 1.0, "confidenceOpacity": null, "frame": null, "x": 728.2198441028595, "y": 1240.5401229858398}]}, {"screenId": 389, "screenTap": [{"confidence": 1.0, "confidenceOpacity": null, "frame": null, "x": 727.4514877796173, "y": 1241.7218399047852}]}, {"screenId": 390, "screenTap": [{"confidence": 1.0, "confidenceOpacity": null, "frame": null, "x": 727.51788854599, "y": 1241.6880798339844}]}, {"screenId": 391, "screenTap": [{"confidence": 1.0, "confidenceOpacity": null, "frame": null, "x": 728.0321645736694, "y": 1241.6078567504883}]}, {"screenId": 392, "screenTap": [{"confidence": 0.9999997615814209, "confidenceOpacity": null, "frame": null, "x": 728.480715751648, "y": 1241.6973495483398}]}, {"screenId": 393, "screenTap": [{"confidence": 0.9999477863311768, "confidenceOpacity": null, "frame": null, "x": 729.5284831523895, "y": 1241.5819931030273}]}, {"screenId": 684, "screenTap": [{"confidence": 1.0, "confidenceOpacity": null, "frame": null, "x": 544.5288509130478, "y": 1422.7795028686523}]}, {"screenId": 685, "screenTap": [{"confidence": 1.0, "confidenceOpacity": null, "frame": null, "x": 544.5836001634598, "y": 1422.8045654296875}]}, {"screenId": 686, "screenTap": [{"confidence": 1.0, "confidenceOpacity": null, "frame": null, "x": 546.700587272644, "y": 1421.0529327392578}]}, {"screenId": 687, "screenTap": [{"confidence": 1.0, "confidenceOpacity": null, "frame": null, "x": 553.5081142187119, "y": 1375.0922012329102}]}, {"screenId": 688, "screenTap": [{"confidence": 1.0, "confidenceOpacity": null, "frame": null, "x": 554.3013346195221, "y": 1262.9433059692383}]}, {"screenId": 689, "screenTap": [{"confidence": 1.0, "confidenceOpacity": null, "frame": null, "x": 554.4286161661148, "y": 1153.8249206542969}]}, {"screenId": 690, "screenTap": [{"confidence": 1.0, "confidenceOpacity": null, "frame": null, "x": 554.5689171552658, "y": 1038.409080505371}]}, {"screenId": 691, "screenTap": [{"confidence": 1.0, "confidenceOpacity": null, "frame": null, "x": 561.239265203476, "y": 963.6979007720947}]}, {"screenId": 692, "screenTap": [{"confidence": 1.0, "confidenceOpacity": null, "frame": null, "x": 582.8694999217987, "y": 886.607551574707}]}, {"screenId": 693, "screenTap": [{"confidence": 1.0, "confidenceOpacity": null, "frame": null, "x": 588.7934267520905, "y": 825.5298614501953}]}, {"screenId": 694, "screenTap": [{"confidence": 1.0, "confidenceOpacity": null, "frame": null, "x": 603.4591770172119, "y": 767.178955078125}]}, {"screenId": 695, "screenTap": [{"confidence": 1.0, "confidenceOpacity": null, "frame": null, "x": 603.4207463264465, "y": 767.2380638122559}]}, {"screenId": 696, "screenTap": [{"confidence": 1.0, "confidenceOpacity": null, "frame": null, "x": 613.0575478076935, "y": 748.2596397399902}]}, {"screenId": 697, "screenTap": [{"confidence": 1.0, "confidenceOpacity": null, "frame": null, "x": 611.3856196403503, "y": 743.573169708252}]}, {"screenId": 698, "screenTap": [{"confidence": 1.0, "confidenceOpacity": null, "frame": null, "x": 612.7596616744995, "y": 742.1735572814941}]}, {"screenId": 699, "screenTap": [{"confidence": 1.0, "confidenceOpacity": null, "frame": null, "x": 613.8018929958344, "y": 740.3253936767578}]}, {"screenId": 700, "screenTap": [{"confidence": 1.0, "confidenceOpacity": null, "frame": null, "x": 613.914223909378, "y": 739.148998260498}]}, {"screenId": 701, "screenTap": [{"confidence": 1.0, "confidenceOpacity": null, "frame": null, "x": 613.913322687149, "y": 739.4096946716309}]}, {"screenId": 702, "screenTap": [{"confidence": 1.0, "confidenceOpacity": null, "frame": null, "x": 613.8530373573303, "y": 740.4241561889648}]}, {"screenId": 703, "screenTap": [{"confidence": 1.0, "confidenceOpacity": null, "frame": null, "x": 613.5450768470764, "y": 740.4952812194824}]}, {"screenId": 704, "screenTap": [{"confidence": 1.0, "confidenceOpacity": null, "frame": null, "x": 613.5962212085724, "y": 739.6297645568848}]}, {"screenId": 705, "screenTap": [{"confidence": 1.0, "confidenceOpacity": null, "frame": null, "x": 613.4874951839447, "y": 739.8714637756348}]}, {"screenId": 706, "screenTap": [{"confidence": 1.0, "confidenceOpacity": null, "frame": null, "x": 612.3047053813934, "y": 739.6376609802246}]}, {"screenId": 707, "screenTap": [{"confidence": 1.0, "confidenceOpacity": null, "frame": null, "x": 612.2249794006348, "y": 739.5106315612793}]}, {"screenId": 708, "screenTap": [{"confidence": 1.0, "confidenceOpacity": null, "frame": null, "x": 612.1495020389557, "y": 740.046558380127}]}, {"screenId": 709, "screenTap": [{"confidence": 0.9999998807907104, "confidenceOpacity": null, "frame": null, "x": 612.0684242248535, "y": 740.1421165466309}]}, {"screenId": 722, "screenTap": [{"confidence": 1.0, "confidenceOpacity": null, "frame": null, "x": 639.374588727951, "y": 1304.9386596679688}]}, {"screenId": 723, "screenTap": [{"confidence": 1.0, "confidenceOpacity": null, "frame": null, "x": 651.0277462005615, "y": 1261.5359115600586}]}, {"screenId": 724, "screenTap": [{"confidence": 1.0, "confidenceOpacity": null, "frame": null, "x": 689.0998148918152, "y": 1087.8941345214844}]}, {"screenId": 725, "screenTap": [{"confidence": 1.0, "confidenceOpacity": null, "frame": null, "x": 694.1192364692688, "y": 1040.7157516479492}]}, {"screenId": 726, "screenTap": [{"confidence": 1.0, "confidenceOpacity": null, "frame": null, "x": 694.9715995788574, "y": 954.0394592285156}]}, {"screenId": 727, "screenTap": [{"confidence": 1.0, "confidenceOpacity": null, "frame": null, "x": 695.3268098831177, "y": 864.8187446594238}]}, {"screenId": 728, "screenTap": [{"confidence": 1.0, "confidenceOpacity": null, "frame": null, "x": 694.4518840312958, "y": 850.6442642211914}]}, {"screenId": 729, "screenTap": [{"confidence": 1.0, "confidenceOpacity": null, "frame": null, "x": 694.9665784835815, "y": 773.0574417114258}]}, {"screenId": 730, "screenTap": [{"confidence": 1.0, "confidenceOpacity": null, "frame": null, "x": 695.2456676959991, "y": 766.36962890625}]}, {"screenId": 731, "screenTap": [{"confidence": 1.0, "confidenceOpacity": null, "frame": null, "x": 694.9362909793854, "y": 766.4057350158691}]}, {"screenId": 732, "screenTap": [{"confidence": 1.0, "confidenceOpacity": null, "frame": null, "x": 694.9872422218323, "y": 766.4379501342773}]}, {"screenId": 733, "screenTap": [{"confidence": 1.0, "confidenceOpacity": null, "frame": null, "x": 694.7372174263, "y": 766.548900604248}]}, {"screenId": 734, "screenTap": [{"confidence": 1.0, "confidenceOpacity": null, "frame": null, "x": 694.9974131584167, "y": 766.7721176147461}]}, {"screenId": 735, "screenTap": [{"confidence": 1.0, "confidenceOpacity": null, "frame": null, "x": 695.574871301651, "y": 766.6495513916016}]}, {"screenId": 736, "screenTap": [{"confidence": 1.0, "confidenceOpacity": null, "frame": null, "x": 695.3941762447357, "y": 766.820240020752}]}, {"screenId": 737, "screenTap": [{"confidence": 1.0, "confidenceOpacity": null, "frame": null, "x": 695.7336151599884, "y": 766.3727188110352}]}, {"screenId": 738, "screenTap": [{"confidence": 1.0, "confidenceOpacity": null, "frame": null, "x": 695.1320493221283, "y": 766.1080741882324}]}, {"screenId": 739, "screenTap": [{"confidence": 1.0, "confidenceOpacity": null, "frame": null, "x": 695.3541362285614, "y": 765.6682205200195}]}, {"screenId": 740, "screenTap": [{"confidence": 0.9999998807907104, "confidenceOpacity": null, "frame": null, "x": 695.5421698093414, "y": 764.9021530151367}]}, {"screenId": 837, "screenTap": [{"confidence": 1.0, "confidenceOpacity": null, "frame": null, "x": 527.0744132995605, "y": 1334.791030883789}]}, {"screenId": 838, "screenTap": [{"confidence": 1.0, "confidenceOpacity": null, "frame": null, "x": 537.6716440916061, "y": 1294.4317245483398}]}, {"screenId": 839, "screenTap": [{"confidence": 1.0, "confidenceOpacity": null, "frame": null, "x": 560.7837456464767, "y": 1194.4655227661133}]}, {"screenId": 840, "screenTap": [{"confidence": 1.0, "confidenceOpacity": null, "frame": null, "x": 622.9050743579865, "y": 954.1660022735596}]}, {"screenId": 841, "screenTap": [{"confidence": 1.0, "confidenceOpacity": null, "frame": null, "x": 626.6061365604401, "y": 917.0226287841797}]}, {"screenId": 842, "screenTap": [{"confidence": 1.0, "confidenceOpacity": null, "frame": null, "x": 626.6609179973602, "y": 915.6897926330566}]}, {"screenId": 843, "screenTap": [{"confidence": 0.978653073310852, "confidenceOpacity": null, "frame": null, "x": 628.974677324295, "y": 916.3714027404785}]}, {"screenId": 867, "screenTap": [{"confidence": 1.0, "confidenceOpacity": null, "frame": null, "x": 562.5472283363342, "y": 1163.9825820922852}]}, {"screenId": 868, "screenTap": [{"confidence": 1.0, "confidenceOpacity": null, "frame": null, "x": 562.4932676553726, "y": 1163.9773178100586}]}, {"screenId": 869, "screenTap": [{"confidence": 0.9999997615814209, "confidenceOpacity": null, "frame": null, "x": 561.4340901374817, "y": 1069.9652481079102}]}, {"screenId": 870, "screenTap": [{"confidence": 0.9999998807907104, "confidenceOpacity": null, "frame": null, "x": 561.5937513113022, "y": 1070.1628875732422}]}, {"screenId": 871, "screenTap": [{"confidence": 1.0, "confidenceOpacity": null, "frame": null, "x": 562.119260430336, "y": 945.8948993682861}]}, {"screenId": 872, "screenTap": [{"confidence": 1.0, "confidenceOpacity": null, "frame": null, "x": 562.1446877717972, "y": 945.8994197845459}]}, {"screenId": 873, "screenTap": [{"confidence": 1.0, "confidenceOpacity": null, "frame": null, "x": 562.1514791250229, "y": 945.9233665466309}]}, {"screenId": 874, "screenTap": [{"confidence": 1.0, "confidenceOpacity": null, "frame": null, "x": 562.1425473690033, "y": 945.9371280670166}]}, {"screenId": 875, "screenTap": [{"confidence": 1.0, "confidenceOpacity": null, "frame": null, "x": 562.2164797782898, "y": 945.1833057403564}]}, {"screenId": 876, "screenTap": [{"confidence": 1.0, "confidenceOpacity": null, "frame": null, "x": 562.1537482738495, "y": 945.1966094970703}]}, {"screenId": 877, "screenTap": [{"confidence": 1.0, "confidenceOpacity": null, "frame": null, "x": 561.5960204601288, "y": 945.2238750457764}]}, {"screenId": 878, "screenTap": [{"confidence": 1.0, "confidenceOpacity": null, "frame": null, "x": 560.3835225105286, "y": 944.4636726379395}]}, {"screenId": 879, "screenTap": [{"confidence": 1.0, "confidenceOpacity": null, "frame": null, "x": 560.3815269470215, "y": 944.4140338897705}]}, {"screenId": 880, "screenTap": [{"confidence": 1.0, "confidenceOpacity": null, "frame": null, "x": 560.7977467775345, "y": 944.2012596130371}]}, {"screenId": 881, "screenTap": [{"confidence": 1.0, "confidenceOpacity": null, "frame": null, "x": 561.4541745185852, "y": 944.106559753418}]}, {"screenId": 882, "screenTap": [{"confidence": 1.0, "confidenceOpacity": null, "frame": null, "x": 561.5056729316711, "y": 944.1016101837158}]}, {"screenId": 883, "screenTap": [{"confidence": 1.0, "confidenceOpacity": null, "frame": null, "x": 561.5817940235138, "y": 943.8852596282959}]}, {"screenId": 884, "screenTap": [{"confidence": 0.9999932050704956, "confidenceOpacity": null, "frame": null, "x": 560.2045977115631, "y": 946.7912864685059}]}, {"screenId": 885, "screenTap": [{"confidence": 0.9999195337295532, "confidenceOpacity": null, "frame": null, "x": 560.2441388368607, "y": 945.9420204162598}]}, {"screenId": 902, "screenTap": [{"confidence": 1.0, "confidenceOpacity": null, "frame": null, "x": 476.0205280780792, "y": 1078.0106735229492}]}, {"screenId": 903, "screenTap": [{"confidence": 1.0, "confidenceOpacity": null, "frame": null, "x": 476.0190153121948, "y": 1078.0582809448242}]}, {"screenId": 904, "screenTap": [{"confidence": 1.0, "confidenceOpacity": null, "frame": null, "x": 475.88999569416046, "y": 1078.0474090576172}]}, {"screenId": 905, "screenTap": [{"confidence": 0.9999998807907104, "confidenceOpacity": null, "frame": null, "x": 475.98991870880127, "y": 1078.2035064697266}]}, {"screenId": 906, "screenTap": [{"confidence": 0.9999998807907104, "confidenceOpacity": null, "frame": null, "x": 476.02439045906067, "y": 1078.223648071289}]}, {"screenId": 907, "screenTap": [{"confidence": 0.9999998807907104, "confidenceOpacity": null, "frame": null, "x": 476.17336571216583, "y": 1078.5915756225586}]}, {"screenId": 908, "screenTap": [{"confidence": 0.9999998807907104, "confidenceOpacity": null, "frame": null, "x": 476.2222409248352, "y": 1078.5918045043945}]}, {"screenId": 1030, "screenTap": [{"confidence": 1.0, "confidenceOpacity": null, "frame": null, "x": 917.8240299224854, "y": 129.6147072315216}]}, {"screenId": 1031, "screenTap": [{"confidence": 1.0, "confidenceOpacity": null, "frame": null, "x": 917.8552830219269, "y": 129.5946979522705}]}, {"screenId": 1032, "screenTap": [{"confidence": 1.0, "confidenceOpacity": null, "frame": null, "x": 917.8013706207275, "y": 129.61679935455322}]}, {"screenId": 1033, "screenTap": [{"confidence": 1.0, "confidenceOpacity": null, "frame": null, "x": 917.7736902236938, "y": 129.60558414459229}]}, {"screenId": 1034, "screenTap": [{"confidence": 1.0, "confidenceOpacity": null, "frame": null, "x": 917.7736902236938, "y": 129.60565567016602}]}, {"screenId": 1035, "screenTap": [{"confidence": 1.0, "confidenceOpacity": null, "frame": null, "x": 917.0310187339783, "y": 129.4159698486328}]}, {"screenId": 1036, "screenTap": [{"confidence": 1.0, "confidenceOpacity": null, "frame": null, "x": 915.6728768348694, "y": 130.4175853729248}]}, {"screenId": 1037, "screenTap": [{"confidence": 1.0, "confidenceOpacity": null, "frame": null, "x": 916.7353534698486, "y": 130.05437850952148}]}, {"screenId": 1038, "screenTap": [{"confidence": 1.0, "confidenceOpacity": null, "frame": null, "x": 916.8694424629211, "y": 130.6915247440338}]}, {"screenId": 1039, "screenTap": [{"confidence": 0.9999998807907104, "confidenceOpacity": null, "frame": null, "x": 916.8901705741882, "y": 130.4637050628662}]}, {"screenId": 1192, "screenTap": [{"confidence": 1.0, "confidenceOpacity": null, "frame": null, "x": 922.5651669502258, "y": 151.76635265350342}]}, {"screenId": 1193, "screenTap": [{"confidence": 1.0, "confidenceOpacity": null, "frame": null, "x": 922.5616586208344, "y": 151.78772449493408}]}, {"screenId": 1194, "screenTap": [{"confidence": 1.0, "confidenceOpacity": null, "frame": null, "x": 922.5406408309937, "y": 151.75480842590332}]}, {"screenId": 1195, "screenTap": [{"confidence": 1.0, "confidenceOpacity": null, "frame": null, "x": 922.3185217380524, "y": 151.43656253814697}]}, {"screenId": 1196, "screenTap": [{"confidence": 1.0, "confidenceOpacity": null, "frame": null, "x": 922.0926368236542, "y": 151.6639280319214}]}, {"screenId": 1197, "screenTap": [{"confidence": 1.0, "confidenceOpacity": null, "frame": null, "x": 922.4136328697205, "y": 151.90024495124817}]}, {"screenId": 1198, "screenTap": [{"confidence": 1.0, "confidenceOpacity": null, "frame": null, "x": 922.3301088809967, "y": 151.4258050918579}]}, {"screenId": 1199, "screenTap": [{"confidence": 0.9999996423721313, "confidenceOpacity": null, "frame": null, "x": 924.9659264087677, "y": 152.74816989898682}]}, {"screenId": 1200, "screenTap": [{"confidence": 0.8223515152931213, "confidenceOpacity": null, "frame": null, "x": 926.0936772823334, "y": 151.63360118865967}]}]